Metadata-Version: 1.1
Name: happycowler
Version: 0.2.4
Summary: Crawl the HappyCow database to GPX or KML files for offline use.
Home-page: https://github.com/peterwittek/happycowler/
Author: Peter Wittek
Author-email: peterwittek@users.noreply.github.com
License: LICENSE
Keywords: vegan,vegetarian,happycow.net,crawler,kml,gpx
Platform: UNKNOWN
Classifier: License :: OSI Approved :: GNU General Public License v3 (GPLv3)
Classifier: Operating System :: OS Independent
Classifier: Intended Audience :: End Users/Desktop
Classifier: Development Status :: 4 - Beta
Classifier: Programming Language :: Python
